cstation_wsloh160220/__init__.py
cstation_wsloh160220/cstation.py
cstation_wsloh160220/commands/container.py
cstation_wsloh160220/commands/flowise.py
cstation_wsloh160220/commands/github.py
cstation_wsloh160220/commands/odoo.py
cstation_wsloh160220/commands/perfectwork.py
cstation_wsloh160220/commands/perfectwork6.py
cstation_wsloh160220/commands/streamlit.py
cstation_wsloh160220-0.1.4.dist-info/METADATA
cstation_wsloh160220-0.1.4.dist-info/WHEEL
cstation_wsloh160220-0.1.4.dist-info/licenses/LICENSE
cstation_wsloh160220-0.1.4.dist-info/RECORD
