Metadata-Version: 2.3
Name: cstation_wsloh160220
Version: 0.1.4
Summary: ANSIS CStation Package
Project-URL: Homepage, https://github.com/ansis-ai/cstation.git
Project-URL: Issues, https://github.com/ansis-ai/cstation/issues
Author-email: Willy <wilson@ansis.com.sg>
License-File: LICENSE
Classifier: License :: OSI Approved :: MIT License
Classifier: Operating System :: OS Independent
Classifier: Programming Language :: Python :: 3
Requires-Python: >=3.8
